src/__init__.py
src/bin/account.py
src/bin/alerts.py
src/bin/api_key.py
src/bin/follower.py
src/bin/follower_request.py
src/bin/following.py
src/bin/following_request.py
src/bin/invites.py
src/bin/member.py
src/bin/member_invite.py
src/bin/organization.py
src/bin/scan.py
src/bin/scan_target.py
src/bin/scan_target_groups.py
src/bin/summary.py
src/config/sdk.py
src/lib/awsorgrun.py
src/lib/docs/README.md
src/lib/dummy_aws_credentials
src/lib/models.py
src/lib/utils.py
src/lib/version.py
src/main.py
zanshincli/main.py
zanshincli-2.2.8.dist-info/METADATA
zanshincli-2.2.8.dist-info/WHEEL
zanshincli-2.2.8.dist-info/entry_points.txt
zanshincli-2.2.8.dist-info/licenses/LICENSE
zanshincli-2.2.8.dist-info/RECORD
