Metadata-Version: 2.4
Name: zanshincli
Version: 2.2.8
Summary: Python command line utility to the Tenchi Security Zanshin API v1
License: Apache Software License
License-File: LICENSE
Author: Tenchi Security
Author-email: contact@tenchisecurity.com
Requires-Python: >=3.10,<4.0
Classifier: Development Status :: 5 - Production/Stable
Classifier: Environment :: Other Environment
Classifier: Intended Audience :: Developers
Classifier: Intended Audience :: System Administrators
Classifier: License :: OSI Approved :: Apache Software License
Classifier: License :: Other/Proprietary License
Classifier: Natural Language :: English
Classifier: Operating System :: OS Independent
Classifier: Programming Language :: Python
Classifier: Programming Language :: Python :: 3
Classifier: Programming Language :: Python :: 3.10
Classifier: Programming Language :: Python :: 3.11
Classifier: Programming Language :: Python :: 3.12
Classifier: Programming Language :: Python :: 3.13
Classifier: Programming Language :: Python :: 3.14
Classifier: Topic :: Security
Requires-Dist: boto3 (>=1.26.8)
Requires-Dist: boto3-type-annotations (>=0.3.1)
Requires-Dist: poetry-plugin-export (>=1.8.0,<2.0.0)
Requires-Dist: prettytable (==3.5.0)
Requires-Dist: typer (==0.7.0)
Requires-Dist: urllib3 (>=1.26.20,<2.0.0)
Requires-Dist: zanshinsdk (==2.2)
Project-URL: Homepage, https://github.com/tenchi-security/zanshin-cli
